[{"jamCuaca":"2024-06-17 00:00:00","kodeCuaca":"1","cuaca":"Cerah Berawan","humidity":"80","tempC":"27","tempF":"81"},{"jamCuaca":"2024-06-17 06:00:00","kodeCuaca":"95","cuaca":"Hujan Petir","humidity":"60","tempC":"33","tempF":"91"},{"jamCuaca":"2024-06-17 12:00:00","kodeCuaca":"3","cuaca":"Berawan","humidity":"85","tempC":"26","tempF":"79"},{"jamCuaca":"2024-06-17 18:00:00","kodeCuaca":"60","cuaca":"Hujan Ringan","humidity":"95","tempC":"24","tempF":"75"},{"jamCuaca":"2024-06-18 00:00:00","kodeCuaca":"3","cuaca":"Berawan","humidity":"80","tempC":"27","tempF":"81"},{"jamCuaca":"2024-06-18 06:00:00","kodeCuaca":"95","cuaca":"Hujan Petir","humidity":"60","tempC":"33","tempF":"91"},{"jamCuaca":"2024-06-18 12:00:00","kodeCuaca":"3","cuaca":"Berawan","humidity":"90","tempC":"25","tempF":"77"},{"jamCuaca":"2024-06-18 18:00:00","kodeCuaca":"1","cuaca":"Cerah Berawan","humidity":"95","tempC":"24","tempF":"75"}]